<?xml version="1.0" encoding="UTF-8"?>
<Networks computer="ROTHARIN" GlobalFPPProxy="" GlobalForceLocalIP="">
  <suppressframes frames="20"/>
  <Controller Id="-1" Name="Falcon F16v3 Serial Port 2" Description="House and Right Yard (128 ch)" Type="Ethernet" Vendor="Falcon" Model="F16V3" Variant="One Expansion Board" AutoSize="0" FullxLightsControl="TRUE" DefaultBrightnessUnderFullControl="100" DefaultGammaUnderFullControl="1" ActiveState="Active" AutoLayout="0" AutoUpload="0" SuppressDuplicates="0" IP="10.3.12.12" Protocol="E131" FPPProxy="" Priority="100" Version="1" Expanded="TRUE" UPS="FALSE" ForceLocalIP="">
    <network ComPort="10.3.12.12" BaudRate="2" NetworkType="E131" MaxChannels="128"/>
  </Controller>
  <Controller Id="2" Name="Falcon F16v3 Serial Port 3" Description="House &amp; Right Yard DMX/AC-DC (128 ch)" Type="Ethernet" Vendor="Falcon" Model="F16V3" Variant="One Expansion Board" AutoSize="0" FullxLightsControl="TRUE" DefaultBrightnessUnderFullControl="100" DefaultGammaUnderFullControl="1" ActiveState="Active" AutoLayout="0" AutoUpload="0" SuppressDuplicates="0" IP="10.3.12.12" Protocol="E131" FPPProxy="" Priority="100" Version="1" Expanded="TRUE" UPS="FALSE" ForceLocalIP="">
    <network ComPort="10.3.12.12" BaudRate="1" NetworkType="E131" MaxChannels="128"/>
  </Controller>
  <Controller Id="-1" Name="Falcon F16v3 Output 01" Description="Eaves Left Horizontal (216 nodes)" Type="Ethernet" Vendor="Falcon" Model="F16V3" Variant="One Expansion Board" AutoSize="0" FullxLightsControl="TRUE" DefaultBrightnessUnderFullControl="100" DefaultGammaUnderFullControl="1" ActiveState="Active" AutoLayout="1" AutoUpload="0" SuppressDuplicates="0" IP="10.3.12.12" Protocol="E131" FPPProxy="" Priority="100" Version="1" Expanded="TRUE" UPS="FALSE" ForceLocalIP="">
    <network ComPort="10.3.12.12" BaudRate="4" NetworkType="E131" MaxChannels="510"/>
    <network ComPort="10.3.12.12" BaudRate="5" NetworkType="E131" MaxChannels="138"/>
  </Controller>
  <Controller Id="2" Name="Falcon F16v3 Output 02" Description="Eaves Left Diagonal (188 nodes)" Type="Ethernet" Vendor="Falcon" Model="F16V3" Variant="One Expansion Board" AutoSize="0" FullxLightsControl="TRUE" DefaultBrightnessUnderFullControl="100" DefaultGammaUnderFullControl="1" ActiveState="Active" AutoLayout="1" AutoUpload="0" SuppressDuplicates="0" IP="10.3.12.12" Protocol="E131" FPPProxy="" Priority="100" Version="1" Expanded="TRUE" UPS="FALSE" ForceLocalIP="">
    <network ComPort="10.3.12.12" BaudRate="6" NetworkType="E131" MaxChannels="510"/>
    <network ComPort="10.3.12.12" BaudRate="7" NetworkType="E131" MaxChannels="54"/>
  </Controller>
  <Controller Id="2" Name="Falcon F16v3 Output 03" Description="Eaves Right Diagonal (184 nodes)" Type="Ethernet" Vendor="Falcon" Model="F16V3" Variant="One Expansion Board" AutoSize="0" FullxLightsControl="TRUE" DefaultBrightnessUnderFullControl="100" DefaultGammaUnderFullControl="1" ActiveState="Active" AutoLayout="1" AutoUpload="0" SuppressDuplicates="0" IP="10.3.12.12" Protocol="E131" FPPProxy="" Priority="100" Version="1" Expanded="TRUE" UPS="FALSE" ForceLocalIP="">
    <network ComPort="10.3.12.12" BaudRate="8" NetworkType="E131" MaxChannels="510"/>
    <network ComPort="10.3.12.12" BaudRate="9" NetworkType="E131" MaxChannels="42"/>
  </Controller>
  <Controller Id="2" Name="Falcon F16v3 Output 04" Description="Eaves Right Horizontal (250 nodes)" Type="Ethernet" Vendor="Falcon" Model="F16V3" Variant="One Expansion Board" AutoSize="0" FullxLightsControl="TRUE" DefaultBrightnessUnderFullControl="100" DefaultGammaUnderFullControl="1" ActiveState="Active" AutoLayout="1" AutoUpload="0" SuppressDuplicates="0" IP="10.3.12.12" Protocol="E131" FPPProxy="" Priority="100" Version="1" Expanded="TRUE" UPS="FALSE" ForceLocalIP="">
    <network ComPort="10.3.12.12" BaudRate="10" NetworkType="E131" MaxChannels="510"/>
    <network ComPort="10.3.12.12" BaudRate="11" NetworkType="E131" MaxChannels="240"/>
  </Controller>
  <Controller Id="2" Name="Falcon F16v3 Output 05" Description="Pixel Tree Front Center (309 nodes)" Type="Ethernet" Vendor="Falcon" Model="F16V3" Variant="One Expansion Board" AutoSize="0" FullxLightsControl="TRUE" DefaultBrightnessUnderFullControl="100" DefaultGammaUnderFullControl="1" ActiveState="Active" AutoLayout="1" AutoUpload="0" SuppressDuplicates="0" IP="10.3.12.12" Protocol="E131" FPPProxy="" Priority="100" Version="1" Expanded="TRUE" UPS="FALSE" ForceLocalIP="">
    <network ComPort="10.3.12.12" BaudRate="12" NetworkType="E131" MaxChannels="510"/>
    <network ComPort="10.3.12.12" BaudRate="13" NetworkType="E131" MaxChannels="417"/>
  </Controller>
  <Controller Id="2" Name="Falcon F16v3 Output 06" Description="Pixel Tree Right Front (309 nodes)" Type="Ethernet" Vendor="Falcon" Model="F16V3" Variant="One Expansion Board" AutoSize="0" FullxLightsControl="TRUE" DefaultBrightnessUnderFullControl="100" DefaultGammaUnderFullControl="1" ActiveState="Active" AutoLayout="1" AutoUpload="0" SuppressDuplicates="0" IP="10.3.12.12" Protocol="E131" FPPProxy="" Priority="100" Version="1" Expanded="TRUE" UPS="FALSE" ForceLocalIP="">
    <network ComPort="10.3.12.12" BaudRate="14" NetworkType="E131" MaxChannels="510"/>
    <network ComPort="10.3.12.12" BaudRate="15" NetworkType="E131" MaxChannels="417"/>
  </Controller>
  <Controller Id="2" Name="Falcon F16v3 Output 07" Description="Snowflakes (4 X 36 = 144 nodes)" Type="Ethernet" Vendor="Falcon" Model="F16V3" Variant="One Expansion Board" AutoSize="0" FullxLightsControl="TRUE" DefaultBrightnessUnderFullControl="100" DefaultGammaUnderFullControl="1" ActiveState="Active" AutoLayout="1" AutoUpload="0" SuppressDuplicates="0" IP="10.3.12.12" Protocol="E131" FPPProxy="" Priority="100" Version="1" Expanded="TRUE" UPS="FALSE" ForceLocalIP="">
    <network ComPort="10.3.12.12" BaudRate="16" NetworkType="E131" MaxChannels="432"/>
  </Controller>
  <Controller Id="2" Name="Falcon F16v3 Output 08" Description="(Spare 5V)" Type="Ethernet" Vendor="Falcon" Model="F16V3" Variant="One Expansion Board" AutoSize="0" FullxLightsControl="TRUE" DefaultBrightnessUnderFullControl="100" DefaultGammaUnderFullControl="1" ActiveState="Active" AutoLayout="1" AutoUpload="0" SuppressDuplicates="0" IP="10.3.12.12" Protocol="E131" FPPProxy="" Priority="100" Version="1" Expanded="TRUE" UPS="FALSE" ForceLocalIP="">
    <network ComPort="10.3.12.12" BaudRate="18" NetworkType="E131" MaxChannels="3"/>
  </Controller>
  <Controller Id="3" Name="Falcon F16v3 Output 09" Description="Singing Tree Left Female (254 nodes)" Type="Ethernet" Vendor="Falcon" Model="F16V3" Variant="One Expansion Board" AutoSize="0" FullxLightsControl="TRUE" DefaultBrightnessUnderFullControl="100" DefaultGammaUnderFullControl="1" ActiveState="Active" AutoLayout="1" AutoUpload="0" SuppressDuplicates="0" IP="10.3.12.12" Protocol="E131" FPPProxy="" Priority="100" Version="1" Expanded="TRUE" UPS="FALSE" ForceLocalIP="">
    <network ComPort="10.3.12.12" BaudRate="20" NetworkType="E131" MaxChannels="510"/>
    <network ComPort="10.3.12.12" BaudRate="21" NetworkType="E131" MaxChannels="252"/>
  </Controller>
  <Controller Id="3" Name="Falcon F16v3 Output 10" Description="Singing Tree Right Male (254 nodes)" Type="Ethernet" Vendor="Falcon" Model="F16V3" Variant="One Expansion Board" AutoSize="0" FullxLightsControl="TRUE" DefaultBrightnessUnderFullControl="100" DefaultGammaUnderFullControl="1" ActiveState="Active" AutoLayout="1" AutoUpload="0" SuppressDuplicates="0" IP="10.3.12.12" Protocol="E131" FPPProxy="" Priority="100" Version="1" Expanded="TRUE" UPS="FALSE" ForceLocalIP="">
    <network ComPort="10.3.12.12" BaudRate="22" NetworkType="E131" MaxChannels="510"/>
    <network ComPort="10.3.12.12" BaudRate="23" NetworkType="E131" MaxChannels="252"/>
  </Controller>
  <Controller Id="2" Name="Falcon F16v3 Output 11" Description="(Spare 12V)" Type="Ethernet" Vendor="Falcon" Model="F16V3" Variant="One Expansion Board" AutoSize="0" FullxLightsControl="TRUE" DefaultBrightnessUnderFullControl="100" DefaultGammaUnderFullControl="1" ActiveState="Active" AutoLayout="1" AutoUpload="0" SuppressDuplicates="1" IP="10.3.12.12" Protocol="E131" FPPProxy="" Priority="100" Version="1" Expanded="TRUE" UPS="FALSE" ForceLocalIP="">
    <network ComPort="10.3.12.12" BaudRate="24" NetworkType="E131" MaxChannels="3"/>
  </Controller>
  <Controller Id="2" Name="Falcon F16v3 Output 12" Description="Starlight Mint Spinners (4 X 85 = 340 nodes)" Type="Ethernet" Vendor="Falcon" Model="F16V3" Variant="One Expansion Board" AutoSize="0" FullxLightsControl="TRUE" DefaultBrightnessUnderFullControl="100" DefaultGammaUnderFullControl="1" ActiveState="Active" AutoLayout="1" AutoUpload="0" SuppressDuplicates="0" IP="10.3.12.12" Protocol="E131" FPPProxy="" Priority="100" Version="1" Expanded="TRUE" UPS="FALSE" ForceLocalIP="">
    <network ComPort="10.3.12.12" BaudRate="26" NetworkType="E131" MaxChannels="510"/>
    <network ComPort="10.3.12.12" BaudRate="27" NetworkType="E131" MaxChannels="510"/>
  </Controller>
  <Controller Id="2" Name="Falcon F16v3 Output 13" Description="Star of David Coro (66 nodes)" Type="Ethernet" Vendor="Falcon" Model="F16V3" Variant="One Expansion Board" AutoSize="0" FullxLightsControl="TRUE" DefaultBrightnessUnderFullControl="100" DefaultGammaUnderFullControl="1" ActiveState="Active" AutoLayout="1" AutoUpload="0" SuppressDuplicates="0" IP="10.3.12.12" Protocol="E131" FPPProxy="" Priority="100" Version="1" Expanded="TRUE" UPS="FALSE" ForceLocalIP="">
    <network ComPort="10.3.12.12" BaudRate="28" NetworkType="E131" MaxChannels="198"/>
  </Controller>
  <Controller Id="2" Name="Falcon F16v3 Output 14" Description="Pixel Fence Swags (21 X 16 = 336 nodes)" Type="Ethernet" Vendor="Falcon" Model="F16V3" Variant="One Expansion Board" AutoSize="0" FullxLightsControl="TRUE" DefaultBrightnessUnderFullControl="100" DefaultGammaUnderFullControl="1" ActiveState="Active" AutoLayout="1" AutoUpload="0" SuppressDuplicates="0" IP="10.3.12.12" Protocol="E131" FPPProxy="" Priority="100" Version="1" Expanded="TRUE" UPS="FALSE" ForceLocalIP="">
    <network ComPort="10.3.12.12" BaudRate="30" NetworkType="E131" MaxChannels="510"/>
    <network ComPort="10.3.12.12" BaudRate="31" NetworkType="E131" MaxChannels="498"/>
  </Controller>
  <Controller Id="2" Name="Falcon F16v3 Output 15" Description="RBLs &amp; Stars (140ish nodes)" Type="Ethernet" Vendor="Falcon" Model="F16V3" Variant="One Expansion Board" AutoSize="0" FullxLightsControl="TRUE" DefaultBrightnessUnderFullControl="100" DefaultGammaUnderFullControl="1" ActiveState="Active" AutoLayout="1" AutoUpload="0" SuppressDuplicates="0" IP="10.3.12.12" Protocol="E131" FPPProxy="" Priority="100" Version="1" Expanded="TRUE" UPS="FALSE" ForceLocalIP="">
    <network ComPort="10.3.12.12" BaudRate="32" NetworkType="E131" MaxChannels="420"/>
  </Controller>
  <Controller Id="2" Name="Falcon F16v3 Output 16" Description="Star Wreath (105 nodes)" Type="Ethernet" Vendor="Falcon" Model="F16V3" Variant="One Expansion Board" AutoSize="0" FullxLightsControl="TRUE" DefaultBrightnessUnderFullControl="100" DefaultGammaUnderFullControl="1" ActiveState="Active" AutoLayout="1" AutoUpload="0" SuppressDuplicates="0" IP="10.3.12.12" Protocol="E131" FPPProxy="" Priority="100" Version="1" Expanded="TRUE" UPS="FALSE" ForceLocalIP="">
    <network ComPort="10.3.12.12" BaudRate="34" NetworkType="E131" MaxChannels="315"/>
  </Controller>
  <Controller Id="2" Name="Falcon F16v3 Remote 1 Output 17" Description="(Spare 12V)" Type="Ethernet" Vendor="Falcon" Model="F16V3" Variant="One Expansion Board" AutoSize="0" FullxLightsControl="TRUE" DefaultBrightnessUnderFullControl="100" DefaultGammaUnderFullControl="1" ActiveState="Inactive" AutoLayout="1" AutoUpload="0" SuppressDuplicates="0" IP="10.3.12.12" Protocol="E131" FPPProxy="" Priority="100" Version="1" Expanded="TRUE" UPS="FALSE" ForceLocalIP="">
    <network ComPort="10.3.12.12" BaudRate="36" NetworkType="E131" MaxChannels="3"/>
  </Controller>
  <Controller Id="2" Name="Falcon F16v3 Remote 1 Output 18" Description="(Spare 12V)" Type="Ethernet" Vendor="Falcon" Model="F16V3" Variant="One Expansion Board" AutoSize="0" FullxLightsControl="TRUE" DefaultBrightnessUnderFullControl="100" DefaultGammaUnderFullControl="1" ActiveState="Inactive" AutoLayout="1" AutoUpload="0" SuppressDuplicates="0" IP="10.3.12.12" Protocol="E131" FPPProxy="" Priority="100" Version="1" Expanded="TRUE" UPS="FALSE" ForceLocalIP="">
    <network ComPort="10.3.12.12" BaudRate="38" NetworkType="E131" MaxChannels="3"/>
  </Controller>
  <Controller Id="3" Name="Falcon F16v3 Remote 1 Output 19" Description="(Spare)" Type="Ethernet" Vendor="Falcon" Model="F16V3" Variant="One Expansion Board" AutoSize="0" DefaultBrightnessUnderFullControl="10" DefaultGammaUnderFullControl="1" ActiveState="Inactive" AutoLayout="0" AutoUpload="0" SuppressDuplicates="0" IP="10.3.12.12" Protocol="E131" FPPProxy="" Priority="100" Version="1" Expanded="TRUE" UPS="FALSE" ForceLocalIP="">
    <network ComPort="10.3.12.12" BaudRate="40" NetworkType="E131" MaxChannels="3"/>
  </Controller>
  <Controller Id="3" Name="Falcon F16v3 Remote 1 Output 20" Description="(Spare)" Type="Ethernet" Vendor="Falcon" Model="F16V3" Variant="One Expansion Board" AutoSize="0" FullxLightsControl="TRUE" DefaultBrightnessUnderFullControl="100" DefaultGammaUnderFullControl="1" ActiveState="Inactive" AutoLayout="1" AutoUpload="0" SuppressDuplicates="0" IP="10.3.12.12" Protocol="E131" FPPProxy="" Priority="100" Version="1" Expanded="TRUE" UPS="FALSE" ForceLocalIP="">
    <network ComPort="10.3.12.12" BaudRate="42" NetworkType="E131" MaxChannels="3"/>
  </Controller>
  <Controller Id="3" Name="Falcon F16v3 Remote 2 Output 21" Description="(Spare)" Type="Ethernet" Vendor="Falcon" Model="F16V3" Variant="One Expansion Board" AutoSize="0" FullxLightsControl="TRUE" DefaultBrightnessUnderFullControl="100" DefaultGammaUnderFullControl="1" ActiveState="Inactive" AutoLayout="1" AutoUpload="0" SuppressDuplicates="0" IP="10.3.12.12" Protocol="E131" FPPProxy="" Priority="100" Version="1" Expanded="TRUE" UPS="FALSE" ForceLocalIP="">
    <network ComPort="10.3.12.12" BaudRate="44" NetworkType="E131" MaxChannels="3"/>
  </Controller>
  <Controller Id="3" Name="Falcon F16v3 Remote 2 Output 22" Description="(Spare)" Type="Ethernet" Vendor="Falcon" Model="F16V3" Variant="One Expansion Board" AutoSize="0" FullxLightsControl="TRUE" DefaultBrightnessUnderFullControl="100" DefaultGammaUnderFullControl="1" ActiveState="Inactive" AutoLayout="1" AutoUpload="0" SuppressDuplicates="0" IP="10.3.12.12" Protocol="E131" FPPProxy="" Priority="100" Version="1" Expanded="TRUE" UPS="FALSE" ForceLocalIP="">
    <network ComPort="10.3.12.12" BaudRate="46" NetworkType="E131" MaxChannels="3"/>
  </Controller>
  <Controller Id="3" Name="Falcon F16v3 Remote 2 Output 23" Description="(Spare)" Type="Ethernet" Vendor="Falcon" Model="F16V3" Variant="One Expansion Board" AutoSize="0" FullxLightsControl="TRUE" DefaultBrightnessUnderFullControl="100" DefaultGammaUnderFullControl="1" ActiveState="Inactive" AutoLayout="1" AutoUpload="0" SuppressDuplicates="0" IP="10.3.12.12" Protocol="E131" FPPProxy="" Priority="100" Version="1" Expanded="TRUE" UPS="FALSE" ForceLocalIP="">
    <network ComPort="10.3.12.12" BaudRate="48" NetworkType="E131" MaxChannels="3"/>
  </Controller>
  <Controller Id="3" Name="Falcon F16v3 Remote 2 Output 24" Description="(Spare)" Type="Ethernet" Vendor="Falcon" Model="F16V3" Variant="One Expansion Board" AutoSize="0" FullxLightsControl="TRUE" DefaultBrightnessUnderFullControl="100" DefaultGammaUnderFullControl="1" ActiveState="Inactive" AutoLayout="1" AutoUpload="0" SuppressDuplicates="0" IP="10.3.12.12" Protocol="E131" FPPProxy="" Priority="100" Version="1" Expanded="TRUE" UPS="FALSE" ForceLocalIP="">
    <network ComPort="10.3.12.12" BaudRate="50" NetworkType="E131" MaxChannels="3"/>
  </Controller>
  <Controller Id="3" Name="Falcon F16v3 Remote 3 Output 25" Description="(Spare)" Type="Ethernet" Vendor="Falcon" Model="F16V3" Variant="One Expansion Board" AutoSize="0" DefaultBrightnessUnderFullControl="100" DefaultGammaUnderFullControl="1" ActiveState="Inactive" AutoLayout="0" AutoUpload="0" SuppressDuplicates="0" IP="10.3.12.12" Protocol="E131" FPPProxy="" Priority="100" Version="1" Expanded="TRUE" UPS="FALSE" ForceLocalIP="">
    <network ComPort="10.3.12.12" BaudRate="52" NetworkType="E131" MaxChannels="3"/>
  </Controller>
  <Controller Id="3" Name="Falcon F16v3 Remote 3 Output 26" Description="(Spare)" Type="Ethernet" Vendor="Falcon" Model="F16V3" Variant="One Expansion Board" AutoSize="0" DefaultBrightnessUnderFullControl="100" DefaultGammaUnderFullControl="1" ActiveState="Inactive" AutoLayout="0" AutoUpload="0" SuppressDuplicates="0" IP="10.3.12.12" Protocol="E131" FPPProxy="" Priority="100" Version="1" Expanded="TRUE" UPS="FALSE" ForceLocalIP="">
    <network ComPort="10.3.12.12" BaudRate="54" NetworkType="E131" MaxChannels="3"/>
  </Controller>
  <Controller Id="3" Name="Falcon F16v3 Remote 3 Output 27" Description="(Spare)" Type="Ethernet" Vendor="Falcon" Model="F16V3" Variant="One Expansion Board" AutoSize="0" DefaultBrightnessUnderFullControl="100" DefaultGammaUnderFullControl="1" ActiveState="Inactive" AutoLayout="0" AutoUpload="0" SuppressDuplicates="0" IP="10.3.12.12" Protocol="E131" FPPProxy="" Priority="100" Version="1" Expanded="TRUE" UPS="FALSE" ForceLocalIP="">
    <network ComPort="10.3.12.12" BaudRate="56" NetworkType="E131" MaxChannels="3"/>
  </Controller>
  <Controller Id="3" Name="Falcon F16v3 Remote 3 Output 28" Description="(Spare)" Type="Ethernet" Vendor="Falcon" Model="F16V3" Variant="One Expansion Board" AutoSize="0" DefaultBrightnessUnderFullControl="100" DefaultGammaUnderFullControl="1" ActiveState="Inactive" AutoLayout="0" AutoUpload="0" SuppressDuplicates="0" IP="10.3.12.12" Protocol="E131" FPPProxy="" Priority="100" Version="1" Expanded="TRUE" UPS="FALSE" ForceLocalIP="">
    <network ComPort="10.3.12.12" BaudRate="58" NetworkType="E131" MaxChannels="3"/>
  </Controller>
  <Controller Id="3" Name="Falcon F16v3 Remote 4 Output 29" Description="Mega Triangle Columns 1-4 (Left)" Type="Ethernet" Vendor="Falcon" Model="F16V3" Variant="One Expansion Board" AutoSize="0" FullxLightsControl="TRUE" DefaultBrightnessUnderFullControl="100" DefaultGammaUnderFullControl="1" ActiveState="Inactive" AutoLayout="0" AutoUpload="0" SuppressDuplicates="0" IP="10.3.12.12" Protocol="E131" FPPProxy="" Priority="100" Version="1" Expanded="TRUE" UPS="FALSE" ForceLocalIP="">
    <network ComPort="10.3.12.12" BaudRate="60" NetworkType="E131" MaxChannels="510"/>
    <network ComPort="10.3.12.12" BaudRate="61" NetworkType="E131" MaxChannels="510"/>
    <network ComPort="10.3.12.12" BaudRate="62" NetworkType="E131" MaxChannels="180"/>
  </Controller>
  <Controller Id="3" Name="Falcon F16v3 Remote 4 Output 30" Description="Mega Triangle Columns 5-8" Type="Ethernet" Vendor="Falcon" Model="F16V3" Variant="One Expansion Board" AutoSize="0" FullxLightsControl="TRUE" DefaultBrightnessUnderFullControl="100" DefaultGammaUnderFullControl="1" ActiveState="Inactive" AutoLayout="0" AutoUpload="0" SuppressDuplicates="0" IP="10.3.12.12" Protocol="E131" FPPProxy="" Priority="100" Version="1" Expanded="TRUE" UPS="FALSE" ForceLocalIP="">
    <network ComPort="10.3.12.12" BaudRate="63" NetworkType="E131" MaxChannels="510"/>
    <network ComPort="10.3.12.12" BaudRate="64" NetworkType="E131" MaxChannels="510"/>
    <network ComPort="10.3.12.12" BaudRate="65" NetworkType="E131" MaxChannels="180"/>
  </Controller>
  <Controller Id="3" Name="Falcon F16v3 Remote 4 Output 31" Description="Mega Triangle Columns 9-12" Type="Ethernet" Vendor="Falcon" Model="F16V3" Variant="One Expansion Board" AutoSize="0" FullxLightsControl="TRUE" DefaultBrightnessUnderFullControl="100" DefaultGammaUnderFullControl="1" ActiveState="Inactive" AutoLayout="0" AutoUpload="0" SuppressDuplicates="0" IP="10.3.12.12" Protocol="E131" FPPProxy="" Priority="100" Version="1" Expanded="TRUE" UPS="FALSE" ForceLocalIP="">
    <network ComPort="10.3.12.12" BaudRate="66" NetworkType="E131" MaxChannels="510"/>
    <network ComPort="10.3.12.12" BaudRate="67" NetworkType="E131" MaxChannels="510"/>
    <network ComPort="10.3.12.12" BaudRate="68" NetworkType="E131" MaxChannels="180"/>
  </Controller>
  <Controller Id="3" Name="Falcon F16v3 Remote 4 Output 32" Description="Mega Triangle Columns 13-16 (Right)" Type="Ethernet" Vendor="Falcon" Model="F16V3" Variant="One Expansion Board" AutoSize="0" FullxLightsControl="TRUE" DefaultBrightnessUnderFullControl="100" DefaultGammaUnderFullControl="1" ActiveState="Inactive" AutoLayout="0" AutoUpload="0" SuppressDuplicates="0" IP="10.3.12.12" Protocol="E131" FPPProxy="" Priority="100" Version="1" Expanded="TRUE" UPS="FALSE" ForceLocalIP="">
    <network ComPort="10.3.12.12" BaudRate="69" NetworkType="E131" MaxChannels="510"/>
    <network ComPort="10.3.12.12" BaudRate="70" NetworkType="E131" MaxChannels="510"/>
    <network ComPort="10.3.12.12" BaudRate="71" NetworkType="E131" MaxChannels="180"/>
  </Controller>
  <Controller Id="3" Name="WLED Wemos #1 Output 1" Description="Sorcerer's Apprentice (150 nodes)" Type="Ethernet" Vendor="WLED" Model="WLED" Variant="Generic ESP8266" AutoSize="0" FullxLightsControl="TRUE" DefaultBrightnessUnderFullControl="100" DefaultGammaUnderFullControl="1" ActiveState="Active" AutoLayout="1" AutoUpload="0" SuppressDuplicates="0" IP="10.3.12.7" Protocol="E131" FPPProxy="" Priority="100" Version="1" Expanded="TRUE" UPS="FALSE" ForceLocalIP="">
    <network ComPort="10.3.12.7" BaudRate="72" NetworkType="E131" MaxChannels="450"/>
  </Controller>
  <Controller Id="3" Name="WLED Wemos #2 Output 1" Description="Star of Bethelehem (106 nodes)" Type="Ethernet" Vendor="WLED" Model="WLED" Variant="Generic ESP8266" AutoSize="0" FullxLightsControl="TRUE" DefaultBrightnessUnderFullControl="100" DefaultGammaUnderFullControl="1" ActiveState="Active" AutoLayout="0" AutoUpload="0" SuppressDuplicates="0" IP="10.3.12.13" Protocol="E131" FPPProxy="" Priority="100" Version="1" Expanded="TRUE" UPS="FALSE" ForceLocalIP="">
    <network ComPort="10.3.12.13" BaudRate="73" NetworkType="E131" MaxChannels="318"/>
  </Controller>
  <Controller Id="3" Name="WLED Wemos #3 Output 1" Description="Wheel of Dharma (128 nodes)" Type="Ethernet" Vendor="WLED" Model="WLED" Variant="Generic ESP8266" AutoSize="0" FullxLightsControl="TRUE" DefaultBrightnessUnderFullControl="100" DefaultGammaUnderFullControl="1" ActiveState="Active" AutoLayout="0" AutoUpload="0" SuppressDuplicates="0" IP="10.3.12.14" Protocol="E131" FPPProxy="" Priority="100" Version="1" Expanded="TRUE" UPS="FALSE" ForceLocalIP="">
    <network ComPort="10.3.12.14" BaudRate="74" NetworkType="E131" MaxChannels="384"/>
  </Controller>
  <Controller Id="3" Name="WLED Wemos #4 Output 1" Description="Major Award (158 nodes)" Type="Ethernet" Vendor="WLED" Model="WLED" Variant="Generic ESP8266" AutoSize="0" FullxLightsControl="TRUE" DefaultBrightnessUnderFullControl="100" DefaultGammaUnderFullControl="1" ActiveState="Active" AutoLayout="0" AutoUpload="0" SuppressDuplicates="0" IP="10.3.12.15" Protocol="E131" FPPProxy="" Priority="100" Version="1" Expanded="TRUE" UPS="FALSE" ForceLocalIP="">
    <network ComPort="10.3.12.15" BaudRate="75" NetworkType="E131" MaxChannels="474"/>
  </Controller>
  <Controller Id="3" Name="WLED Wemos #5 Output 1" Description="Small Text Matrix Donations Left Half" Type="Ethernet" Vendor="WLED" Model="WLED" Variant="Generic ESP8266" AutoSize="0" FullxLightsControl="TRUE" DefaultBrightnessUnderFullControl="100" DefaultGammaUnderFullControl="1" ActiveState="Inactive" AutoLayout="0" AutoUpload="0" SuppressDuplicates="0" IP="10.3.12.16" Protocol="E131" FPPProxy="" Priority="100" Version="1" Expanded="TRUE" UPS="FALSE" ForceLocalIP="">
    <network ComPort="10.3.12.16" BaudRate="76" NetworkType="E131" MaxChannels="510"/>
    <network ComPort="10.3.12.16" BaudRate="77" NetworkType="E131" MaxChannels="258"/>
  </Controller>
  <Controller Id="3" Name="WLED Wemos #5 Output 2" Description="Small Text Matrix Donations Right Half" Type="Ethernet" Vendor="WLED" Model="WLED" Variant="Generic ESP8266" AutoSize="0" FullxLightsControl="TRUE" DefaultBrightnessUnderFullControl="100" DefaultGammaUnderFullControl="1" ActiveState="Inactive" AutoLayout="0" AutoUpload="0" SuppressDuplicates="0" IP="10.3.12.16" Protocol="E131" FPPProxy="" Priority="100" Version="1" Expanded="TRUE" UPS="FALSE" ForceLocalIP="">
    <network ComPort="10.3.12.16" BaudRate="78" NetworkType="E131" MaxChannels="510"/>
    <network ComPort="10.3.12.16" BaudRate="79" NetworkType="E131" MaxChannels="258"/>
  </Controller>
  <Controller Id="3" Name="WLED Wemos #6 Output 1" Description="(Spare)" Type="Ethernet" Vendor="WLED" Model="WLED" Variant="Generic ESP8266" AutoSize="0" FullxLightsControl="TRUE" DefaultBrightnessUnderFullControl="100" DefaultGammaUnderFullControl="1" ActiveState="Inactive" AutoLayout="0" AutoUpload="0" SuppressDuplicates="0" IP="10.3.12.17" Protocol="E131" FPPProxy="" Priority="100" Version="1" Expanded="TRUE" UPS="FALSE" ForceLocalIP="">
    <network ComPort="10.3.12.17" BaudRate="80" NetworkType="E131" MaxChannels="3"/>
    <network ComPort="10.3.12.17" BaudRate="81" NetworkType="E131" MaxChannels="3"/>
  </Controller>
  <Controller Id="3" Name="(Reserved) Tune To Sign" Description="" Type="Ethernet" Vendor="" Model="" Variant="" AutoSize="0" FullxLightsControl="TRUE" DefaultBrightnessUnderFullControl="100" DefaultGammaUnderFullControl="1" ActiveState="Inactive" AutoLayout="1" AutoUpload="0" SuppressDuplicates="0" IP="10.3.12.18" Protocol="E131" FPPProxy="" Priority="100" Version="1" Expanded="TRUE" UPS="FALSE" ForceLocalIP="">
    <network ComPort="10.3.12.18" BaudRate="82" NetworkType="E131" MaxChannels="3"/>
  </Controller>
  <Controller Id="3" Name="WLED Eth01 #1 Output 1" Description="Big Text Matrix Rows 1-4 (Top)" Type="Ethernet" Vendor="WLED" Model="WLED" Variant="Generic ESP32" AutoSize="0" FullxLightsControl="TRUE" DefaultBrightnessUnderFullControl="100" DefaultGammaUnderFullControl="1" ActiveState="Inactive" AutoLayout="0" AutoUpload="0" SuppressDuplicates="0" IP="10.3.12.20" Protocol="E131" FPPProxy="" Priority="100" Version="1" Expanded="TRUE" UPS="FALSE" ForceLocalIP="">
    <network ComPort="10.3.12.20" BaudRate="88" NetworkType="E131" MaxChannels="510"/>
    <network ComPort="10.3.12.20" BaudRate="89" NetworkType="E131" MaxChannels="354"/>
  </Controller>
  <Controller Id="3" Name="WLED Eth01 #1 Output 2" Description="Big Text Matrix Rows 5-8" Type="Ethernet" Vendor="WLED" Model="WLED" Variant="Generic ESP32" AutoSize="0" FullxLightsControl="TRUE" DefaultBrightnessUnderFullControl="100" DefaultGammaUnderFullControl="1" ActiveState="Inactive" AutoLayout="0" AutoUpload="0" SuppressDuplicates="0" IP="10.3.12.20" Protocol="E131" FPPProxy="" Priority="100" Version="1" Expanded="TRUE" UPS="FALSE" ForceLocalIP="">
    <network ComPort="10.3.12.20" BaudRate="90" NetworkType="E131" MaxChannels="510"/>
    <network ComPort="10.3.12.20" BaudRate="91" NetworkType="E131" MaxChannels="354"/>
  </Controller>
  <Controller Id="3" Name="WLED Eth01 #1 Output 3" Description="Big Text Matrix Rows 9-12" Type="Ethernet" Vendor="WLED" Model="WLED" Variant="Generic ESP32" AutoSize="0" FullxLightsControl="TRUE" DefaultBrightnessUnderFullControl="100" DefaultGammaUnderFullControl="1" ActiveState="Inactive" AutoLayout="0" AutoUpload="0" SuppressDuplicates="0" IP="10.3.12.20" Protocol="E131" FPPProxy="" Priority="100" Version="1" Expanded="TRUE" UPS="FALSE" ForceLocalIP="">
    <network ComPort="10.3.12.20" BaudRate="92" NetworkType="E131" MaxChannels="510"/>
    <network ComPort="10.3.12.20" BaudRate="93" NetworkType="E131" MaxChannels="354"/>
  </Controller>
  <Controller Id="3" Name="WLED Eth01 #1 Output 4" Description="Big Text Matrix Rows 13-16 (Bottom)" Type="Ethernet" Vendor="WLED" Model="WLED" Variant="Generic ESP32" AutoSize="0" FullxLightsControl="TRUE" DefaultBrightnessUnderFullControl="100" DefaultGammaUnderFullControl="1" ActiveState="Inactive" AutoLayout="0" AutoUpload="0" SuppressDuplicates="0" IP="10.3.12.20" Protocol="E131" FPPProxy="" Priority="100" Version="1" Expanded="TRUE" UPS="FALSE" ForceLocalIP="">
    <network ComPort="10.3.12.20" BaudRate="94" NetworkType="E131" MaxChannels="510"/>
    <network ComPort="10.3.12.20" BaudRate="95" NetworkType="E131" MaxChannels="354"/>
  </Controller>
  <Controller Id="3" Name="zNull or Retired Placeholder" Description="Placeholders for Null or Retired Props" Type="Ethernet" Vendor="" Model="" Variant="" AutoSize="0" FullxLightsControl="TRUE" DefaultBrightnessUnderFullControl="100" DefaultGammaUnderFullControl="1" ActiveState="Inactive" AutoLayout="1" AutoUpload="0" SuppressDuplicates="0" IP="10.3.12.253" Protocol="E131" FPPProxy="" Priority="100" Version="1" Expanded="TRUE" UPS="FALSE" ForceLocalIP="">
    <network ComPort="10.3.12.253" BaudRate="10000" NetworkType="E131" MaxChannels="20"/>
  </Controller>
</Networks>
